peekplus/__init__.py
peekplus/__main__.py
peekplus/bin/ffmpeg
peekplus/bin/ffmpeg.exe
peekplus/icon/camera.svg
peekplus/icon/caret-down-fill.svg
peekplus/icon/cursor.svg
peekplus/icon/fullscreen-exit.svg
peekplus/icon/fullscreen.svg
peekplus/icon/gear-fill.svg
peekplus/icon/gear.svg
peekplus/icon/record-fill.svg
peekplus/icon/stop-fill.svg
peekplus/icon/x.svg
peekplus-2.1.8.dist-info/METADATA
peekplus-2.1.8.dist-info/WHEEL
peekplus-2.1.8.dist-info/licenses/LICENSE
peekplus-2.1.8.dist-info/RECORD
