Metadata-Version: 2.1
Name: peekplus
Version: 2.1.8
Summary: An animated GIF recorder
Project-URL: Homepage, https://github.com/firatkiral/peek
Project-URL: Bug Tracker, https://github.com/firatkiral/peek/issues
Author-email: Firat Kiral <firatkiral@gmail.com>
License-File: LICENSE
Classifier: License :: OSI Approved :: MIT License
Classifier: Operating System :: OS Independent
Classifier: Programming Language :: Python :: 3
Requires-Python: >=3.7
Requires-Dist: pyside6>=6.4.1
